osxcollector/__init__.py
osxcollector/osxcollector.py
osxcollector-1.12.dist-info/LICENSE.md
osxcollector-1.12.dist-info/METADATA
osxcollector-1.12.dist-info/WHEEL
osxcollector-1.12.dist-info/entry_points.txt
osxcollector-1.12.dist-info/top_level.txt
osxcollector-1.12.dist-info/RECORD
