Metadata-Version: 2.1
Name: osxcollector
Version: 1.12
Summary: A tool for answering "How'd that malware get there?"
Home-page: https://github.com/Yelp/osxcollector
Author: Yelp Security
Author-email: opensource@yelp.com
License: GNU General Public License
Platform: UNKNOWN
Requires-Dist: macholib (>=1.7)
Requires-Dist: pyobjc (>=3.0.4)
Requires-Dist: xattr (>=0.8.0)
